CHANGELOG.rst
LICENSE.txt
MANIFEST.in
README.rst
setup.cfg
setup.py
tableaurest/__init__.py
tableaurest/__main__.py
tableaurest/cli.py
tableaurest/core.py
tableaurest.egg-info/PKG-INFO
tableaurest.egg-info/SOURCES.txt
tableaurest.egg-info/dependency_links.txt
tableaurest.egg-info/entry_points.txt
tableaurest.egg-info/requires.txt
tableaurest.egg-info/top_level.txt