Metadata-Version: 1.2
Name: tableaurest
Version: 0.3.0
Summary: A Python based Tableau REST API interface.
Home-page: UNKNOWN
Author: Levi Kanwischer
Author-email: hello@levibrooks.co
License: MIT license
Keywords: Tableau,Tableau REST API,TabCMD
Platform: UNKNOWN
Classifier: Development Status :: 3 - Alpha
Classifier: Intended Audience :: Developers
Classifier: Natural Language :: English
Classifier: Programming Language :: Python
Classifier: Programming Language :: Python :: 3.6
Classifier: Programming Language :: Python :: 3 :: Only
Requires-Python: >=3.6
